LICENSE.txt
MANIFEST.in
README.rst
VERSION
setup.cfg
setup.py
0.0.1.egg-info/PKG-INFO
0.0.1.egg-info/SOURCES.txt
0.0.1.egg-info/dependency_links.txt
0.0.1.egg-info/entry_points.txt
0.0.1.egg-info/requires.txt
0.0.1.egg-info/top_level.txt
image2tfrecords/__init__.py
image2tfrecords/image2tfrecords.py
image2tfrecords/imagedataset.py
image2tfrecords/settings.py