Metadata-Version: 1.1
Name: 0.0.1
Version: 0.0.1
Summary: A lib for creating tensorflow tfrecords
Home-page: https://github.com/scotthuang1989/image2tfrecords
Author: scott huang
Author-email: scotthuang1989@163.com
License: GPL-3.0
Keywords: tensorflow tfrecord
Platform: UNKNOWN
Classifier: Development Status :: 3 - Alpha
Classifier: Intended Audience :: Developers
Classifier: Topic :: Software Development :: Build Tools
Classifier: License :: OSI Approved :: GNU General Public License v3 (GPLv3)
Classifier: Programming Language :: Python :: 3.5
